edgar/__init__.py
edgar/utils/__init__.py
edgar/utils/backfill/__init__.py
edgar/utils/backfill/optimization.py
edgar/utils/backfill/optimization_files.py
edgar/utils/date/__init__.py
edgar/utils/date/date_utils.py
edgar/utils/date/holidays.py
edgar/utils/repo/__init__.py
edgar/utils/repo/file_object_locator.py
edgar/utils/repo/file_repo_dir.py
edgar/utils/repo/file_repo_fs.py
edgar/utils/repo/file_repo_object.py
edgar/utils/repo/http_repo_fs.py
edgar/utils/repo/repo.py
edgar/utils/repo/repo_fs.py
edgar_utils-0.0.5.dist-info/LICENSE.txt
edgar_utils-0.0.5.dist-info/METADATA
edgar_utils-0.0.5.dist-info/WHEEL
edgar_utils-0.0.5.dist-info/top_level.txt
edgar_utils-0.0.5.dist-info/RECORD
