Metadata-Version: 2.1
Name: edgar-utils
Version: 0.0.5
Summary: Utils to load financials filing from Edgar
Home-page: https://pypi.org/project/edgar-utils/
Author: Aleksey Beregov
Author-email: beregov@teladictum.com
License: LICENSE.txt
Platform: UNKNOWN
Classifier: Development Status :: 4 - Beta
Classifier: Intended Audience :: Developers
Classifier: Topic :: Software Development :: Build Tools
Classifier: License :: OSI Approved :: MIT License
Classifier: Programming Language :: Python :: 3.6
Requires-Python: >=3.6
Requires-Dist: pytest
Requires-Dist: pytest-cov
Requires-Dist: faker
Requires-Dist: parse
Requires-Dist: requests
Requires-Dist: sphinx
